cfgx/__init__.py
cfgx/cli.py
cfgx/config.py
cfgx/py.typed
cfgx-0.4.0.dist-info/WHEEL
cfgx-0.4.0.dist-info/entry_points.txt
cfgx-0.4.0.dist-info/METADATA
cfgx-0.4.0.dist-info/RECORD
