Metadata-Version: 2.3
Name: cfgx
Version: 0.4.0
Summary: Python-first config loader with composition and CLI overrides.
Author: Karim Abou Zeid
Author-email: Karim Abou Zeid <contact@ka.codes>
Requires-Dist: ruff>=0.14.3 ; extra == 'format'
Requires-Python: >=3.10
Provides-Extra: format
